ckanext/__init__.py
ckanext/alias/__init__.py
ckanext/alias/config.py
ckanext/alias/plugin.py
ckanext/alias/utils.py
ckanext/alias/views.py
ckanext/alias/assets/alias-multiple-input.js
ckanext/alias/assets/style.css
ckanext/alias/assets/webassets.yml
ckanext/alias/logic/action.py
ckanext/alias/logic/validators.py
ckanext/alias/templates/page.html
ckanext/alias/templates/scheming/display_snippets/alias.html
ckanext/alias/templates/scheming/form_snippets/alias.html
ckanext/alias/tests/__init__.py
ckanext/alias/tests/test_alias.py
ckanext_alias-1.0.11.dist-info/LICENSE
ckanext_alias-1.0.11.dist-info/METADATA
ckanext_alias-1.0.11.dist-info/WHEEL
ckanext_alias-1.0.11.dist-info/entry_points.txt
ckanext_alias-1.0.11.dist-info/top_level.txt
ckanext_alias-1.0.11.dist-info/RECORD
